mysqlclientpy/__init__.py
mysqlclientpy-1.1.dist-info/METADATA
mysqlclientpy-1.1.dist-info/WHEEL
mysqlclientpy-1.1.dist-info/top_level.txt
mysqlclientpy-1.1.dist-info/RECORD
