Metadata-Version: 2.1
Name: mysqlclientpy
Version: 1.1
Requires-Dist: mysql-connector-python
Requires-Dist: protobuf
